odoo/addons/sale_order_import_ubl_customer_free_ref/README.rst
odoo/addons/sale_order_import_ubl_customer_free_ref/__init__.py
odoo/addons/sale_order_import_ubl_customer_free_ref/__manifest__.py
odoo/addons/sale_order_import_ubl_customer_free_ref/i18n/it.po
odoo/addons/sale_order_import_ubl_customer_free_ref/i18n/sale_order_import_ubl_customer_free_ref.pot
odoo/addons/sale_order_import_ubl_customer_free_ref/readme/CONTRIBUTORS.md
odoo/addons/sale_order_import_ubl_customer_free_ref/readme/DESCRIPTION.md
odoo/addons/sale_order_import_ubl_customer_free_ref/static/description/icon.png
odoo/addons/sale_order_import_ubl_customer_free_ref/static/description/index.html
odoo/addons/sale_order_import_ubl_customer_free_ref/tests/__init__.py
odoo/addons/sale_order_import_ubl_customer_free_ref/tests/test_ubl_order_import.py
odoo/addons/sale_order_import_ubl_customer_free_ref/tests/files/UBL-Order-2.0-Example.xml
odoo/addons/sale_order_import_ubl_customer_free_ref/tests/files/UBL-Order-2.1-Example.xml
odoo/addons/sale_order_import_ubl_customer_free_ref/tests/files/UBL-Order-2.2-Example.xml
odoo/addons/sale_order_import_ubl_customer_free_ref/wizard/__init__.py
odoo/addons/sale_order_import_ubl_customer_free_ref/wizard/sale_order_import.py
odoo_addon_sale_order_import_ubl_customer_free_ref-18.0.1.0.0.3.dist-info/METADATA
odoo_addon_sale_order_import_ubl_customer_free_ref-18.0.1.0.0.3.dist-info/WHEEL
odoo_addon_sale_order_import_ubl_customer_free_ref-18.0.1.0.0.3.dist-info/top_level.txt
odoo_addon_sale_order_import_ubl_customer_free_ref-18.0.1.0.0.3.dist-info/RECORD
